terra_bonobo_nodes/__init__.py
terra_bonobo_nodes/archive.py
terra_bonobo_nodes/common.py
terra_bonobo_nodes/db.py
terra_bonobo_nodes/elasticsearch.py
terra_bonobo_nodes/osm.py
terra_bonobo_nodes/pyfiles.py
terra_bonobo_nodes/shapefile.py
terra_bonobo_nodes/sql.py
terra_bonobo_nodes/terra.py
terra_bonobo_nodes-0.5.2.dist-info/LICENSE
terra_bonobo_nodes-0.5.2.dist-info/METADATA
terra_bonobo_nodes-0.5.2.dist-info/WHEEL
terra_bonobo_nodes-0.5.2.dist-info/dependency_links.txt
terra_bonobo_nodes-0.5.2.dist-info/top_level.txt
terra_bonobo_nodes-0.5.2.dist-info/RECORD
