Metadata-Version: 2.1
Name: terra-bonobo-nodes
Version: 0.5.2
Summary: Set of bonobo ETL's nodes for terralego's projects
Home-page: https://github.com/Terralego/terra-bonobo-nodes
Author: Makina Corpus
Author-email: terralego-pypi@makina-corpus.com
License: UNKNOWN
Platform: UNKNOWN
Classifier: Programming Language :: Python :: 3
Classifier: License :: OSI Approved :: MIT License
Classifier: Operating System :: OS Independent
Requires-Dist: Django (<3.0,>=2.2)
Requires-Dist: django-geostore (>=0.3)
Requires-Dist: requests (>=2.19)
Requires-Dist: bonobo (<0.6.9,>=0.6.0)
Requires-Dist: elasticsearch (<8.0.0,>=7.0.0)
Requires-Dist: psycopg2 (>2.7)
Requires-Dist: pytest (>=4.5.0)
